graphql_server/__init__.py
graphql_server/error.py
graphql_server_core-1.1rc0.dist-info/DESCRIPTION.rst
graphql_server_core-1.1rc0.dist-info/METADATA
graphql_server_core-1.1rc0.dist-info/RECORD
graphql_server_core-1.1rc0.dist-info/WHEEL
graphql_server_core-1.1rc0.dist-info/metadata.json
graphql_server_core-1.1rc0.dist-info/top_level.txt
