Metadata-Version: 2.0
Name: graphql-server-core
Version: 1.1rc0
Summary: GraphQL Server tools for powering your server
Home-page: https://github.com/graphql-python/graphql-server-core
Author: Syrus Akbary
Author-email: me@syrusakbary.com
License: MIT
Download-URL: https://github.com/graphql-python/graphql-server-core/releases
Keywords: api graphql protocol rest
Platform: any
Classifier: Development Status :: 5 - Production/Stable
Classifier: Intended Audience :: Developers
Classifier: Topic :: Software Development :: Libraries
Classifier: Programming Language :: Python :: 2
Classifier: Programming Language :: Python :: 2.7
Classifier: Programming Language :: Python :: 3
Classifier: Programming Language :: Python :: 3.3
Classifier: Programming Language :: Python :: 3.4
Classifier: Programming Language :: Python :: 3.5
Classifier: Programming Language :: Python :: Implementation :: PyPy
Classifier: License :: OSI Approved :: MIT License
Requires-Dist: graphql-core (>=2.1rc1)
Requires-Dist: promise
